cm_course_uos/__init__.py
cm_course_uos/__init__.pyc
cm_course_uos/problemset1.pyc
cm_course_uos/problemset2.pyc
cm_course_uos/problemset3.pyc
cm_course_uos/problemset4.pyc
cm_course_uos/problemset5.pyc
cm_course_uos/__pycache__/__init__.cpython-38.pyc
cm_course_uos/__pycache__/problemset1.cpython-38.pyc
cm_course_uos-2.3.4.dist-info/METADATA
cm_course_uos-2.3.4.dist-info/WHEEL
cm_course_uos-2.3.4.dist-info/top_level.txt
cm_course_uos-2.3.4.dist-info/RECORD
