Metadata-Version: 2.2
Name: cm_course_uos
Version: 2.3.4
Summary: This package hosts code required to run the colab notebooks which host the course assignemnts.
Home-page: https://github.com/denizmgun/cm-course-uos
Author: smusslick,denizmgun,melisaaltinyelek,pelinito,rbastian
Author-email: dguen@uos.de
Classifier: Development Status :: 3 - Alpha
Classifier: License :: OSI Approved :: MIT License
Classifier: Programming Language :: Python :: 3
Dynamic: author
Dynamic: author-email
Dynamic: classifier
Dynamic: description
Dynamic: home-page
Dynamic: summary
